MANIFEST.in
README.md
setup.py
git/__init__.py
git/cmd.py
git/compat.py
git/config.py
git/db.py
git/diff.py
git/exc.py
git/remote.py
git/util.py
git/index/__init__.py
git/index/base.py
git/index/fun.py
git/index/typ.py
git/index/util.py
git/objects/__init__.py
git/objects/base.py
git/objects/blob.py
git/objects/commit.py
git/objects/fun.py
git/objects/tag.py
git/objects/tree.py
git/objects/util.py
git/objects/submodule/__init__.py
git/objects/submodule/base.py
git/objects/submodule/root.py
git/objects/submodule/util.py
git/refs/__init__.py
git/refs/head.py
git/refs/log.py
git/refs/reference.py
git/refs/remote.py
git/refs/symbolic.py
git/refs/tag.py
git/repo/__init__.py
git/repo/base.py
git/repo/fun.py
gitdb/__init__.py
gitdb/base.py
gitdb/const.py
gitdb/exc.py
gitdb/fun.py
gitdb/pack.py
gitdb/stream.py
gitdb/typ.py
gitdb/util.py
gitdb/db/__init__.py
gitdb/db/base.py
gitdb/db/git.py
gitdb/db/loose.py
gitdb/db/mem.py
gitdb/db/pack.py
gitdb/db/ref.py
gitdb/utils/__init__.py
gitdb/utils/compat.py
gitdb/utils/encoding.py
yoctools/__init__.py
yoctools/builder.py
yoctools/cmd.py
yoctools/command.py
yoctools/component.py
yoctools/gitproject.py
yoctools/log.py
yoctools/make.py
yoctools/manifest.py
yoctools/occ.py
yoctools/package.py
yoctools/progress.py
yoctools/qemu.py
yoctools/repo.py
yoctools/solution.py
yoctools/toolchain.py
yoctools/tools.py
yoctools/yoc.py
yoctools.egg-info/PKG-INFO
yoctools.egg-info/SOURCES.txt
yoctools.egg-info/dependency_links.txt
yoctools.egg-info/entry_points.txt
yoctools.egg-info/requires.txt
yoctools.egg-info/top_level.txt
yoctools/build/gen_ldfile.sh
yoctools/build/product.exe
yoctools/build/product32
yoctools/build/product64
yoctools/script/README.md
yoctools/script/after_build.sh
yoctools/script/before_build.sh
yoctools/script/flash.init
yoctools/script/gdbinit
yoctools/site_tools/__init__.py
yoctools/site_tools/objcopy.py
yoctools/site_tools/objdump.py
yoctools/site_tools/product.py
yoctools/subcmds/__init__.py
yoctools/subcmds/addkey.py
yoctools/subcmds/br2tag.py
yoctools/subcmds/branch.py
yoctools/subcmds/cct.py
yoctools/subcmds/cdk.py
yoctools/subcmds/cdkxml.py
yoctools/subcmds/cds.py
yoctools/subcmds/checkout.py
